persistify/__init__.py
persistify/persistify.py
persistify-1.0.dist-info/METADATA
persistify-1.0.dist-info/WHEEL
persistify-1.0.dist-info/entry_points.txt
persistify-1.0.dist-info/licenses/LICENSE
persistify-1.0.dist-info/RECORD
