Metadata-Version: 2.4
Name: Persistify
Version: 1.0
Summary: Library for saving Python data structures as Python code.
Author: SuperWhiteDev
License: MIT License
License-File: LICENSE
Keywords: persistence,python-code,serialization
Classifier: License :: OSI Approved :: MIT License
Classifier: Operating System :: OS Independent
Classifier: Programming Language :: Python :: 3
Requires-Python: >=3.7
Requires-Dist: pycryptodome>=3.10.1
